{
  "total_threats": 86,
  "total_domains": 29,
  "by_severity": {
    "critical": 5,
    "high": 38,
    "medium": 15,
    "low": 28
  },
  "by_intent": {
    "ad_review_bypass": 1,
    "ai_ad_review_evasion": 2,
    "ai_content_moderation_bypass": 1,
    "ai_disruption": 2,
    "ai_memory_poisoning": 1,
    "ai_memory_poisoning_tooling": 1,
    "ai_output_manipulation": 7,
    "anti_ai_protest": 1,
    "anti_scraping": 1,
    "biased_content_generation": 1,
    "biased_promotional_content": 1,
    "data_destruction": 6,
    "donation_solicitation": 1,
    "financial_solicitation": 1,
    "fraudulent_transaction": 1,
    "hiring_manipulation": 1,
    "irrelevant_output": 1,
    "monetization": 1,
    "other": 25,
    "phishing_redirect": 1,
    "sensitive_information_leakage": 2,
    "seo_manipulation": 1,
    "seo_poisoning": 4,
    "seo_poisoning_malware_delivery": 4,
    "unauthorized_transaction": 8,
    "unknown": 10
  },
  "by_source": {
    "htsbp": 20,
    "openclaw": 54,
    "tldrsec": 1,
    "unit42": 11
  },
  "last_updated": "2026-03-23T19:04:18.846Z",
  "generated_at": "2026-03-24T00:44:17.561Z"
}
